[
  {
    "title": "Renault kangoo limited edition tce",
    "brand": "Renault",
    "year_numeric": 2018,
    "mileage_numeric": 42000,
    "price_numeric": 1200.0,
    "url": "https://www.2dehands.be/",
    "source": "2dehands.be",
    "scraped_at": "2025-12-10T07:44:41.282956"
  },
  {
    "title": "Renault kangoo  lichte vracht 1.5 cdi automaat 03/2023",
    "brand": "Renault",
    "year_numeric": 2023,
    "mileage_numeric": 3000,
    "price_numeric": 3000.0,
    "url": "https://www.2dehands.be/",
    "source": "2dehands.be",
    "scraped_at": "2025-12-10T07:44:41.283283"
  },
  {
    "title": "BMW 316",
    "brand": "BMW",
    "year_numeric": 2014,
    "mileage_numeric": 109500,
    "price_numeric": 8000.0,
    "url": "https://www.2dehands.be/",
    "source": "2dehands.be",
    "scraped_at": "2025-12-10T07:44:41.283509"
  },
  {
    "title": "2024 Dodge RAM 1500 V8 Limited Night Edition",
    "brand": null,
    "year_numeric": 2024,
    "mileage_numeric": null,
    "price_numeric": 1500.0,
    "url": "https://www.2dehands.be/",
    "source": "2dehands.be",
    "scraped_at": "2025-12-10T07:44:41.283608"
  },
  {
    "title": "Fiat Fullback Autoutilitare",
    "brand": "Fiat",
    "year_numeric": 2018,
    "mileage_numeric": 170000,
    "price_numeric": 13500.0,
    "url": "https://www.2dehands.be/",
    "source": "2dehands.be",
    "scraped_at": "2025-12-10T07:44:41.283681"
  },
  {
    "title": "Ranger wildtrack 2024 raptor look",
    "brand": null,
    "year_numeric": 2024,
    "mileage_numeric": 100000,
    "price_numeric": 4000.0,
    "url": "https://www.2dehands.be/",
    "source": "2dehands.be",
    "scraped_at": "2025-12-10T07:44:41.283737"
  },
  {
    "title": "Citroen C4 spacetourer 7 zitplatsen",
    "brand": "Citroen",
    "year_numeric": 2021,
    "mileage_numeric": 69000,
    "price_numeric": 20000.0,
    "url": "https://www.2dehands.be/",
    "source": "2dehands.be",
    "scraped_at": "2025-12-10T07:44:41.283801"
  },
  {
    "title": "✅VW Passat 2017 ✅Euro6B✅ €8950✅ met Keuring + onderhoud✅",
    "brand": null,
    "year_numeric": 2017,
    "mileage_numeric": null,
    "price_numeric": 8950.0,
    "url": "https://www.2dehands.be/",
    "source": "2dehands.be",
    "scraped_at": "2025-12-10T07:44:41.283880"
  },
  {
    "title": "Volkswagen Passat 1.6Tdi 2017/185000km/Euro6/NAV/Cam/GEKEURD",
    "brand": "Volkswagen",
    "year_numeric": 2017,
    "mileage_numeric": 185000,
    "price_numeric": 9000.0,
    "url": "https://www.2dehands.be/",
    "source": "2dehands.be",
    "scraped_at": "2025-12-10T07:44:41.284175"
  },
  {
    "title": "BMW 325i * E90 * IN PERFECTE STAAT * SPORTIEVE UITVOERING",
    "brand": "BMW",
    "year_numeric": 2008,
    "mileage_numeric": 2008,
    "price_numeric": 2996.0,
    "url": "https://www.2dehands.be/",
    "source": "2dehands.be",
    "scraped_at": "2025-12-10T07:44:41.284446"
  },
  {
    "title": "Citroen Berlingo XL  09/2021_8400€ netto_Keuring+Garantie",
    "brand": "Citroen",
    "year_numeric": 2021,
    "mileage_numeric": 69183,
    "price_numeric": 8400.0,
    "url": "https://www.2dehands.be/",
    "source": "2dehands.be",
    "scraped_at": "2025-12-10T07:44:41.284669"
  },
  {
    "title": "Peugeot 5008 automaat leder euro 6 1.6 diesel 7 plaatsen",
    "brand": "Peugeot",
    "year_numeric": null,
    "mileage_numeric": null,
    "price_numeric": 5008.0,
    "url": "https://www.2dehands.be/",
    "source": "2dehands.be",
    "scraped_at": "2025-12-10T07:44:44.084953"
  },
  {
    "title": "VW Caddy 2.0 TDI 75kW 102CV 5 zitplaatsen 10/2020",
    "brand": null,
    "year_numeric": 2020,
    "mileage_numeric": 163000,
    "price_numeric": 16500.0,
    "url": "https://www.2dehands.be/",
    "source": "2dehands.be",
    "scraped_at": "2025-12-10T07:44:44.085311"
  },
  {
    "title": "VW Caddy",
    "brand": null,
    "year_numeric": 2019,
    "mileage_numeric": 107400,
    "price_numeric": 17500.0,
    "url": "https://www.2dehands.be/",
    "source": "2dehands.be",
    "scraped_at": "2025-12-10T07:44:44.085717"
  },
  {
  "title": "Automaat benzine 1.6i benzine 155000km",
  "brand": "Renault",  
  "year_numeric": 2009,
  "mileage_numeric": 155000,
  "price_numeric": 4599,  
  "fuel_type": "petrol"  
  
  },
  {
    "title": "Volkswagen Polo 1.0 tsi  carplay  66kw  bwjr 2019. Euro 6d",
    "brand": "Volkswagen",
    "year_numeric": 2019,
    "mileage_numeric": null,
    "price_numeric": 2019.0,
    "url": "https://www.2dehands.be/",
    "source": "2dehands.be",
    "scraped_at": "2025-12-10T07:44:44.086877"
  }
]